nesting99.py
Nesting99-1.1.0.dist-info/METADATA
Nesting99-1.1.0.dist-info/WHEEL
Nesting99-1.1.0.dist-info/top_level.txt
Nesting99-1.1.0.dist-info/RECORD
