Metadata-Version: 2.1
Name: Nesting99
Version: 1.1.0
Summary: Simple printer of nested lists
Home-page: https://github.com/shadw0w23
Author: Adrian
Author-email: shad.w0w@outlook.com
